mcrops/__init__.py
mcrops/rows.py
mcrops/utils.py
mcrops/veget.py
mcrops/weeds.py
mcrops-0.1.0.dist-info/LICENSE
mcrops-0.1.0.dist-info/METADATA
mcrops-0.1.0.dist-info/WHEEL
mcrops-0.1.0.dist-info/top_level.txt
mcrops-0.1.0.dist-info/RECORD
